bc125at_perl_helper/__init__.py
BC125AT_Perl_Helper-1.2.5.dist-info/LICENSE
BC125AT_Perl_Helper-1.2.5.dist-info/METADATA
BC125AT_Perl_Helper-1.2.5.dist-info/WHEEL
BC125AT_Perl_Helper-1.2.5.dist-info/entry_points.txt
BC125AT_Perl_Helper-1.2.5.dist-info/top_level.txt
BC125AT_Perl_Helper-1.2.5.dist-info/RECORD
