Metadata-Version: 2.1
Name: BC125AT-Perl-Helper
Version: 1.2.5
Summary: A tool to convert bc125at-perl's output to CSV and back.
Home-page: https://github.com/itsmaxymoo/bc125at-perl-helper
Author: Max Loiacono
Author-email: 
License: Mozilla Public License version 2.0
Platform: UNKNOWN
Classifier: Programming Language :: Python :: 3
Classifier: License :: OSI Approved :: Mozilla Public License 2.0 (MPL 2.0)
Classifier: Operating System :: OS Independent
Requires-Python: >=3.6
License-File: LICENSE
